{
   "CodeGenerationMode": 2,
   "ContextClassName": "AdventureWorksLTSContext",
   "ContextNamespace": null,
   "DefaultDacpacSchema": null,
   "FilterSchemas": false,
   "IncludeConnectionString": true,
   "ModelNamespace": null,
   "OutputContextPath": null,
   "OutputPath": null,
   "PreserveCasingWithRegex": true,
   "ProjectRootNamespace": "DataAccessLayer",
   "Schemas": null,
   "SelectedHandlebarsLanguage": 0,
   "SelectedToBeGenerated": 0,
   "Tables": [
      {
         "Name": "[dbo].[Address]",
         "ObjectType": 0
      },
      {
         "Name": "[dbo].[Category]",
         "ObjectType": 0
      },
      {
         "Name": "[dbo].[Customer]",
         "ObjectType": 0
      },
      {
         "Name": "[dbo].[CustomerAddress]",
         "ObjectType": 0
      },
      {
         "Name": "[dbo].[Order]",
         "ObjectType": 0
      },
      {
         "Name": "[dbo].[OrderDetail]",
         "ObjectType": 0
      },
      {
         "Name": "[dbo].[Product]",
         "ObjectType": 0
      },
      {
         "Name": "[dbo].[ProductModel]",
         "ObjectType": 0
      }
   ],
   "UiHint": "DESKTOP-OA69V71.AdventureWorksLTS",
   "UseBoolPropertiesWithoutDefaultSql": false,
   "UseDatabaseNames": false,
   "UseDbContextSplitting": false,
   "UseFluentApiOnly": true,
   "UseHandleBars": false,
   "UseHierarchyId": false,
   "UseInflector": true,
   "UseLegacyPluralizer": false,
   "UseManyToManyEntity": false,
   "UseNoConstructor": false,
   "UseNoDefaultConstructor": false,
   "UseNoNavigations": false,
   "UseNoObjectFilter": false,
   "UseNodaTime": false,
   "UseNullableReferences": false,
   "UseSchemaFolders": false,
   "UseSpatial": false,
   "UseT4": false
}